lightning_uq_box/__init__.py
lightning_uq_box/__main__.py
lightning_uq_box/main.py
lightning_uq_box/py.typed
lightning_uq_box/datamodules/__init__.py
lightning_uq_box/datamodules/toy_8_gaussians.py
lightning_uq_box/datamodules/toy_donut.py
lightning_uq_box/datamodules/toy_due.py
lightning_uq_box/datamodules/toy_gaussian_sideways.py
lightning_uq_box/datamodules/toy_half_moons.py
lightning_uq_box/datamodules/toy_heteroscedastic.py
lightning_uq_box/datamodules/toy_image_classification.py
lightning_uq_box/datamodules/toy_image_regression.py
lightning_uq_box/datamodules/toy_image_segmentation.py
lightning_uq_box/datamodules/toy_pixelwise_regression.py
lightning_uq_box/datamodules/toy_sine.py
lightning_uq_box/datamodules/utils.py
lightning_uq_box/datasets/__init__.py
lightning_uq_box/datasets/toy_8_gaussians.py
lightning_uq_box/datasets/toy_donut.py
lightning_uq_box/datasets/toy_gaussian_sideways.py
lightning_uq_box/datasets/toy_image_classification.py
lightning_uq_box/datasets/toy_image_regression.py
lightning_uq_box/datasets/toy_image_segmentation.py
lightning_uq_box/datasets/toy_pixelwise_regression.py
lightning_uq_box/eval_utils/__init__.py
lightning_uq_box/eval_utils/uq_computation.py
lightning_uq_box/models/__init__.py
lightning_uq_box/models/cards.py
lightning_uq_box/models/density_layers.py
lightning_uq_box/models/fc_resnet.py
lightning_uq_box/models/hierarchical_prob_unet.py
lightning_uq_box/models/masked_conv.py
lightning_uq_box/models/mixture_density.py
lightning_uq_box/models/mlp.py
lightning_uq_box/models/prob_unet.py
lightning_uq_box/models/vae.py
lightning_uq_box/models/bnn_layers/__init__.py
lightning_uq_box/models/bnn_layers/base_variational.py
lightning_uq_box/models/bnn_layers/bnn_utils.py
lightning_uq_box/models/bnn_layers/conv_variational.py
lightning_uq_box/models/bnn_layers/linear_variational.py
lightning_uq_box/models/bnn_layers/rnn_layer.py
lightning_uq_box/models/bnnlv/latent_variable_network.py
lightning_uq_box/models/bnnlv/utils.py
lightning_uq_box-0.2.0.dist-info/LICENSE
lightning_uq_box-0.2.0.dist-info/METADATA
lightning_uq_box-0.2.0.dist-info/WHEEL
lightning_uq_box-0.2.0.dist-info/entry_points.txt
lightning_uq_box-0.2.0.dist-info/top_level.txt
lightning_uq_box-0.2.0.dist-info/RECORD
