Metadata-Version: 2.1
Name: lightning-uq-box
Version: 0.2.0
Summary: Lightning-UQ-Box: A toolbox for uncertainty quantification in deep learning
Author-email: Nils Lehmann <n.lehmann@tum.de>
Maintainer-email: Nils Lehmann <n.lehmann@tum.de>
License:                                  Apache License
Keywords: pytorch,lightning,uncertainty quantification,conformal prediction,bayesian deep learning
Classifier: Development Status :: 3 - Alpha
Classifier: Intended Audience :: Science/Research
Classifier: License :: OSI Approved :: Apache Software License
Classifier: Operating System :: OS Independent
Classifier: Programming Language :: Python :: 3
Classifier: Programming Language :: Python :: 3.10
Classifier: Programming Language :: Python :: 3.11
Classifier: Programming Language :: Python :: 3.12
Classifier: Topic :: Scientific/Engineering :: Artificial Intelligence
Requires-Python: >=3.10
License-File: LICENSE
Requires-Dist: einops>=0.3
Requires-Dist: lightning>=2.4.0
Requires-Dist: matplotlib>=3.5
Requires-Dist: numpy>=1.21.1
Requires-Dist: pandas>=1.1.3
Requires-Dist: torch>=2.0
Requires-Dist: torchmetrics>=1.2
Requires-Dist: torchvision>=0.16.1
Requires-Dist: scikit-learn>=1.3
Requires-Dist: gpytorch>=1.11
Requires-Dist: laplace-torch>=0.2.1
Requires-Dist: uncertainty-toolbox>=0.1.1
Requires-Dist: kornia>=0.6.9
Requires-Dist: timm>=0.9.2
Requires-Dist: torchseg>=0.0.1a1
Requires-Dist: h5py>=3.12.1
Requires-Dist: ema-pytorch>=0.7.0
Provides-Extra: tests
Requires-Dist: pytest>=7.3; extra == "tests"
Requires-Dist: pytest-cov>=4; extra == "tests"
Requires-Dist: pytest-lazy-fixture>=0.6; extra == "tests"
Requires-Dist: hydra-core>=1.3.2; extra == "tests"
Requires-Dist: omegaconf>=2.3.0; extra == "tests"
Requires-Dist: jsonargparse[signatures]>=4.28.0; extra == "tests"
Requires-Dist: ruff>=0.2; extra == "tests"
Provides-Extra: docs
Requires-Dist: sphinx<7,>=4; extra == "docs"
Requires-Dist: ipywidgets>=7; extra == "docs"
Requires-Dist: nbsphinx>=0.8.5; extra == "docs"
Requires-Dist: sphinx-book-theme>=1.0.1; extra == "docs"
Requires-Dist: myst-parser>=2.0; extra == "docs"
Requires-Dist: sphinx-togglebutton>=0.3.2; extra == "docs"
Requires-Dist: jupytext>=1.15.2; extra == "docs"
Requires-Dist: ipykernel>=6.29.3; extra == "docs"
